seba_sqlite/__init__.py
seba_sqlite/batch.py
seba_sqlite/calculation_result.py
seba_sqlite/control_definition.py
seba_sqlite/control_value.py
seba_sqlite/database.py
seba_sqlite/exceptions.py
seba_sqlite/experiment.py
seba_sqlite/function.py
seba_sqlite/gradient_result.py
seba_sqlite/py.typed
seba_sqlite/realization.py
seba_sqlite/simulation.py
seba_sqlite/simulation_result.py
seba_sqlite/snapshot.py
seba_sqlite/sqlite_storage.py
seba_sqlite/version.py
seba_sqlite-0.1.2.dist-info/LICENSE
seba_sqlite-0.1.2.dist-info/METADATA
seba_sqlite-0.1.2.dist-info/WHEEL
seba_sqlite-0.1.2.dist-info/top_level.txt
seba_sqlite-0.1.2.dist-info/RECORD
